{"nm":"Final Loop","ddd":0,"h":169,"w":300,"meta":{"g":"@lottiefiles/toolkit-js 0.33.2"},"layers":[{"ty":0,"nm":"Balls","sr":1,"st":36.0000014663101,"op":936.000038124062,"ip":36.0000014663101,"hd":false,"ddd":0,"bm":0,"hasMask":false,"ao":0,"ks":{"a":{"a":0,"k":[150,84.5,0],"ix":1},"s":{"a":0,"k":[100,100,100],"ix":6},"sk":{"a":0,"k":0},"p":{"a":0,"k":[150,84.5,0],"ix":2},"r":{"a":0,"k":0,"ix":10},"sa":{"a":0,"k":0},"o":{"a":0,"k":100,"ix":11}},"ef":[],"w":300,"h":169,"refId":"comp_5","ind":1},{"ty":0,"nm":"Balls","sr":1,"st":18.000000733155,"op":918.000037390907,"ip":18.000000733155,"hd":false,"ddd":0,"bm":0,"hasMask":false,"ao":0,"ks":{"a":{"a":0,"k":[150,84.5,0],"ix":1},"s":{"a":0,"k":[100,100,100],"ix":6},"sk":{"a":0,"k":0},"p":{"a":0,"k":[150,84.5,0],"ix":2},"r":{"a":0,"k":0,"ix":10},"sa":{"a":0,"k":0},"o":{"a":0,"k":100,"ix":11}},"ef":[],"w":300,"h":169,"refId":"comp_5","ind":2},{"ty":0,"nm":"Balls","sr":1,"st":-18.000000733155,"op":882.000035924596,"ip":-18.000000733155,"hd":false,"ddd":0,"bm":0,"hasMask":false,"ao":0,"ks":{"a":{"a":0,"k":[150,84.5,0],"ix":1},"s":{"a":0,"k":[100,100,100],"ix":6},"sk":{"a":0,"k":0},"p":{"a":0,"k":[150,84.5,0],"ix":2},"r":{"a":0,"k":0,"ix":10},"sa":{"a":0,"k":0},"o":{"a":0,"k":100,"ix":11}},"ef":[],"w":300,"h":169,"refId":"comp_5","ind":3},{"ty":0,"nm":"Balls","sr":1,"st":0,"op":900.000036657751,"ip":0,"hd":false,"ddd":0,"bm":0,"hasMask":false,"ao":0,"ks":{"a":{"a":0,"k":[150,84.5,0],"ix":1},"s":{"a":0,"k":[100,100,100],"ix":6},"sk":{"a":0,"k":0},"p":{"a":0,"k":[150,84.5,0],"ix":2},"r":{"a":0,"k":0,"ix":10},"sa":{"a":0,"k":0},"o":{"a":0,"k":100,"ix":11}},"ef":[],"w":300,"h":169,"refId":"comp_5","ind":4}],"v":"5.1.3","fr":29.9700012207031,"op":48.0000019550801,"ip":30.0000012219251,"assets":[{"nm":"","id":"comp_5","layers":[{"ty":4,"nm":"Shape Layer 1","sr":1,"st":0,"op":60.0000024438501,"ip":0,"hd":false,"ddd":0,"bm":0,"hasMask":false,"ao":0,"ks":{"a":{"a":0,"k":[4.249,8.249,0],"ix":1},"s":{"a":1,"k":[{"o":{"x":0.167,"y":0.167},"i":{"x":0.745,"y":1},"s":[0,0,100],"t":0},{"o":{"x":0.237,"y":0},"i":{"x":0.833,"y":0.833},"s":[100,100,100],"t":30},{"s":[0,0,100],"t":60.0000024438501}],"ix":6},"sk":{"a":0,"k":0},"p":{"a":1,"k":[{"o":{"x":0.167,"y":0.167},"i":{"x":0.833,"y":0.833},"s":[34,84,0],"t":0,"ti":[-38.6666679382324,0,0],"to":[38.6666679382324,0,0]},{"s":[266,84,0],"t":60.0000024438501}],"ix":2},"r":{"a":0,"k":0,"ix":10},"sa":{"a":0,"k":0},"o":{"a":0,"k":100,"ix":11}},"ef":[],"shapes":[{"ty":"gr","bm":0,"hd":false,"mn":"ADBE Vector Group","nm":"Ellipse 1","ix":1,"cix":2,"np":2,"it":[{"ty":"sh","bm":0,"hd":false,"mn":"ADBE Vector Shape - Group","nm":"Path 1","ix":1,"d":1,"ks":{"a":0,"k":{"c":true,"i":[[18.087,0],[0,-18.087],[-18.087,0],[0,18.087]],"o":[[-18.087,0],[0,18.087],[18.087,0],[0,-18.087]],"v":[[0,-32.749],[-32.749,0],[0,32.749],[32.749,0]]},"ix":2}},{"ty":"fl","bm":0,"hd":false,"mn":"ADBE Vector Graphic - Fill","nm":"Fill 1","c":{"a":0,"k":[1,0.7961,0.1804],"ix":4},"r":1,"o":{"a":0,"k":100,"ix":5}},{"ty":"tr","a":{"a":0,"k":[0,0],"ix":1},"s":{"a":0,"k":[100,100],"ix":3},"sk":{"a":0,"k":0,"ix":4},"p":{"a":0,"k":[4.249,8.249],"ix":2},"r":{"a":0,"k":0,"ix":6},"sa":{"a":0,"k":0,"ix":5},"o":{"a":0,"k":100,"ix":7}}]}],"ind":1}]}]}